README.md
setup.py
discordpresence.egg-info/PKG-INFO
discordpresence.egg-info/SOURCES.txt
discordpresence.egg-info/dependency_links.txt
discordpresence.egg-info/requires.txt
discordpresence.egg-info/top_level.txt
presence/__init__.py
presence/presence.py