Metadata-Version: 2.1
Name: discordpresence
Version: 1.0.0
Summary: Package to set discord presnece.
Home-page: https://github.com/sscefalix/discordpresence
Download-URL: https://pypi.org/project/discordpresence/
Author: sscefalix
Author-email: dimabykov189@gmail.com
License: MIT
Keywords: Discord,DiscordPresence,Presence
Requires-Python: >=3.8
